tornado_bunny/__init__.py
tornado_bunny/async_adapter.py
tornado_bunny/async_connection.py
tornado_bunny/channel_configuration.py
tornado_bunny/consumer.py
tornado_bunny/intentional_close_channel_error.py
tornado_bunny/publisher.py
tornado_bunny/rabbitmq_connection_data.py
tornado_bunny-1.0.18.dist-info/AUTHORS.rst
tornado_bunny-1.0.18.dist-info/LICENSE
tornado_bunny-1.0.18.dist-info/METADATA
tornado_bunny-1.0.18.dist-info/WHEEL
tornado_bunny-1.0.18.dist-info/top_level.txt
tornado_bunny-1.0.18.dist-info/RECORD
