Metadata-Version: 2.1
Name: tornado-bunny
Version: 1.0.18
Summary: RabbitMQ connector library for Python that is fully integrated with the aio-pika framework
Home-page: https://github.com/odedshimon/tornado-bunny
Author: Oded Shimon
Author-email: audreyr@example.com
License: MIT license
Keywords: tornado_bunny
Platform: UNKNOWN
Classifier: Development Status :: 2 - Pre-Alpha
Classifier: Intended Audience :: Developers
Classifier: License :: OSI Approved :: MIT License
Classifier: Natural Language :: English
Classifier: Programming Language :: Python :: 3
Classifier: Programming Language :: Python :: 3.7
Classifier: Programming Language :: Python :: 3.8
Classifier: Programming Language :: Python :: 3.9
Requires-Python: >=3.7
Requires-Dist: pip (>=19.2.3)
Requires-Dist: bump2version (>=0.5.11)
Requires-Dist: wheel (>=0.33.6)
Requires-Dist: watchdog (>=0.9.0)
Requires-Dist: flake8 (>=3.7.8)
Requires-Dist: tox (>=3.14.0)
Requires-Dist: coverage (>=4.5.4)
Requires-Dist: Sphinx (>=1.8.5)
Requires-Dist: twine (>=1.14.0)
Requires-Dist: pytest (>=4.6.5)
Requires-Dist: pytest-asyncio (>=0.15.1)
Requires-Dist: pytest-runner (>=5.1)
Requires-Dist: aiohttp (>=3.7.4.post0)
Requires-Dist: setuptools (>=57.2.0)
Requires-Dist: aiormq (<4,>=3.2.3)
Requires-Dist: aio-pika (==6.8.0)
